colabcode/__init__.py
colabcode/code.py
colabcode-0.3.0.data/scripts/colabcode
colabcode-0.3.0.dist-info/LICENSE
colabcode-0.3.0.dist-info/METADATA
colabcode-0.3.0.dist-info/WHEEL
colabcode-0.3.0.dist-info/top_level.txt
colabcode-0.3.0.dist-info/RECORD
