Metadata-Version: 2.1
Name: colabcode
Version: 0.3.0
Summary: ColabCode - Run codeserver on Colab!
Home-page: https://github.com/abhishekkrthakur/colabcode
Author: Abhishek Thakur
Author-email: abhishek4@gmail.com
License: MIT License
Platform: linux
Platform: unix
Requires-Python: >3.5.2
